{
  "$schema": "https://vega.github.io/schema/vega-lite/v5.json",
  "title": "CO₂ Emissions in Malaysia and Australia (1995–2018)",
  "data": {"url": "data/co2_emissions_malaysia_australia.json"},
  "mark": "bar",
  "encoding": {
    "x": {"field": "Year", "type": "temporal", "timeUnit": "year", "axis": {"title": "Year"}},
    "y": {"field": "CO2_emissions", "type": "quantitative", "axis": {"title": "CO₂ Emissions (Metric tons)"}},
    "color": {"field": "Country", "type": "nominal", "legend": {"title": "Country"}},
    "tooltip": [
      {"field": "Country", "type": "nominal"},
      {"field": "Year", "type": "temporal"},
      {"field": "CO2_emissions", "type": "quantitative"}
    ]
  },
  "width": 600,
  "height": 400
}
